tf_sentence_transformers/__init__.py
tf_sentence_transformers-0.2.dist-info/LICENSE.md
tf_sentence_transformers-0.2.dist-info/METADATA
tf_sentence_transformers-0.2.dist-info/WHEEL
tf_sentence_transformers-0.2.dist-info/top_level.txt
tf_sentence_transformers-0.2.dist-info/RECORD
