Metadata-Version: 2.1
Name: tf-sentence-transformers
Version: 0.2
Summary: A Tensorflow SentenceTransformer layer that takes in strings as input.
Home-page: https://github.com/zzsi/tf_sentence_transformers
Author: ZZ Si
Author-email: zhangzhang.si@gmail.com
License: MIT
Requires-Python: >=3.6
License-File: LICENSE.md
Requires-Dist: tensorflow (>=2)
Requires-Dist: transformers
